cvisp/__init__.py
cvisp/utils.py
cvisp-0.1.3.dist-info/LICENSE.txt
cvisp-0.1.3.dist-info/METADATA
cvisp-0.1.3.dist-info/WHEEL
cvisp-0.1.3.dist-info/top_level.txt
cvisp-0.1.3.dist-info/RECORD
